<WorkflowProcess><Activities><Activity id="1" type="START_NODE" name="StartNode" xCoordinate="51" yCoordinate="14" width="80" height="30"/><Activity id="2" type="END_NODE" name="EndNode" xCoordinate="790" yCoordinate="225" width="80" height="30"/><Activity id="7" type="NODE" name="DOCX to DITA XML" xCoordinate="47" yCoordinate="240" width="80" height="30"/><Activity id="8" type="TASK_NODE" name="XML Generation Failed" xCoordinate="615" yCoordinate="223" width="80" height="30"/><Activity id="9" type="DECISION_NODE" name="Exception Occur?" xCoordinate="270" yCoordinate="64" width="80" height="30"/><Activity id="14" type="TASK_NODE" name="XML Generated" xCoordinate="743" yCoordinate="44" width="80" height="30"/><Activity id="18" type="NODE" name="Set MO Details to Variables" xCoordinate="48" yCoordinate="148" width="80" height="30"/><Activity id="19" type="NODE" name="Set Variables from Properties" xCoordinate="44" yCoordinate="65" width="80" height="30"/><Activity id="21" type="NODE" name="Clear Exception Status" xCoordinate="220" yCoordinate="279" width="80" height="30"/><Activity id="25" type="NODE" name="Load the XML" xCoordinate="444" yCoordinate="45" width="80" height="30"/><Activity id="27" type="DECISION_NODE" name="Load Failed?" xCoordinate="602" yCoordinate="35" width="80" height="30"/><Activity id="32" type="TASK_NODE" name="Load of XML Failed" xCoordinate="631" yCoordinate="128" width="80" height="30"/><Activity id="36" type="NODE" name="Clear Load Exception Status" xCoordinate="457" yCoordinate="96" width="80" height="30"/><Activity id="40" type="NODE" name="Set Parent CA Node to Variable" xCoordinate="174" yCoordinate="10" width="80" height="30"/></Activities><Transitions><Transition id="11" name="true" from="9" to="8"/><Transition id="12" name="" from="7" to="9"/><Transition id="13" name="End workflow" from="8" to="2"/><Transition id="19" name="" from="18" to="7"/><Transition id="21" name="" from="19" to="18"/><Transition id="23" name="" from="21" to="7"/><Transition id="24" name="Retry the Generation" from="8" to="21"/><Transition id="28" name="" from="25" to="27"/><Transition id="29" name="false" from="9" to="25"/><Transition id="30" name="false" from="27" to="14"/><Transition id="31" name="Done" from="14" to="2"/><Transition id="33" name="true" from="27" to="32"/><Transition id="34" name="End workflow" from="32" to="2"/><Transition id="39" name="Retry the load" from="32" to="36"/><Transition id="40" name="" from="36" to="25"/><Transition id="41" name="" from="1" to="40"/><Transition id="42" name="" from="40" to="19"/></Transitions></WorkflowProcess>
